odoo/addons/cms_form_example/README.rst
odoo/addons/cms_form_example/__init__.py
odoo/addons/cms_form_example/__manifest__.py
odoo/addons/cms_form_example/controllers/__init__.py
odoo/addons/cms_form_example/controllers/main.py
odoo/addons/cms_form_example/i18n/cms_form_example.pot
odoo/addons/cms_form_example/models/__init__.py
odoo/addons/cms_form_example/models/partner.py
odoo/addons/cms_form_example/static/description/icon.png
odoo/addons/cms_form_example/static/src/js/cms_form_example.tour.js
odoo/addons/cms_form_example/templates/assets.xml
odoo11_addon_cms_form_example-11.0.1.1.0.dist-info/METADATA
odoo11_addon_cms_form_example-11.0.1.1.0.dist-info/WHEEL
odoo11_addon_cms_form_example-11.0.1.1.0.dist-info/top_level.txt
odoo11_addon_cms_form_example-11.0.1.1.0.dist-info/RECORD
